logdecoratorandhandler/__init__.py
logdecoratorandhandler/log_decorator.py
logdecoratorandhandler/log_handler.py
logdecoratorandhandler/options.py
logdecoratorandhandler-0.3.0.dist-info/WHEEL
logdecoratorandhandler-0.3.0.dist-info/METADATA
logdecoratorandhandler-0.3.0.dist-info/RECORD
