Metadata-Version: 2.1
Name: logdecoratorandhandler
Version: 0.3.0
Summary: Log decorator and handler for logging functions easily
License: MIT
Author: barbara73
Author-email: barbara.jesacher@gmail.com
Requires-Python: >=3.9,<4.0
Classifier: License :: OSI Approved :: MIT License
Classifier: Programming Language :: Python :: 3
Classifier: Programming Language :: Python :: 3.10
Classifier: Programming Language :: Python :: 3.9
